abe/__init__.py
abe/mocks.py
abe/unittest.py
abe/utils.py
abe_python-0.4.0.dist-info/DESCRIPTION.rst
abe_python-0.4.0.dist-info/METADATA
abe_python-0.4.0.dist-info/RECORD
abe_python-0.4.0.dist-info/WHEEL
abe_python-0.4.0.dist-info/metadata.json
abe_python-0.4.0.dist-info/top_level.txt
