Metadata-Version: 2.0
Name: abe-python
Version: 0.4.0
Summary: Parse ABE files for usage within python tests
Home-page: https://github.com/apibyexample/abe-python
Author: Carles Barrobés
Author-email: carles@barrobes.com
License: UNKNOWN
Platform: UNKNOWN
Classifier: Development Status :: 4 - Beta
Classifier: Intended Audience :: Developers
Classifier: License :: OSI Approved :: GNU Library or Lesser General Public License (LGPL)
Classifier: Operating System :: OS Independent
Classifier: Programming Language :: Python
Classifier: Topic :: Software Development :: Testing
Requires-Dist: supermutes (>=0.2.5)
